{
  "openapi": "3.0.1",
  "info": {
    "title": "mixcore - MixCore Services API endpoints (Part 5)",
    "version": "v2"
  },
  "paths": {
    "/api/v2/rest/mix-portal/mixdb-context/patch-many": {
      "patch": {
        "tags": [
          "Portal - mix Database Context"
        ],
        "requestBody": {
          "content": {
            "application/json-patch+json": {
              "schema": {
                "type": "array",
                "items": {
                  "type": "object",
                  "additionalProperties": {
                    "$ref": "#/components/schemas/Newtonsoft.Json.Linq.JToken"
                  }
                }
              }
            },
            "application/json": {
              "schema": {
                "type": "array",
                "items": {
                  "type": "object",
                  "additionalProperties": {
                    "$ref": "#/components/schemas/Newtonsoft.Json.Linq.JToken"
                  }
                }
              }
            },
            "text/json": {
              "schema": {
                "type": "array",
                "items": {
                  "type": "object",
                  "additionalProperties": {
                    "$ref": "#/components/schemas/Newtonsoft.Json.Linq.JToken"
                  }
                }
              }
            },
            "application/*+json": {
              "schema": {
                "type": "array",
                "items": {
                  "type": "object",
                  "additionalProperties": {
                    "$ref": "#/components/schemas/Newtonsoft.Json.Linq.JToken"
                  }
                }
              }
            }
          }
        },
        "responses": {
          "200": {
            "description": "OK"
          }
        }
      }
    },
    "/api/v2/rest/mix-portal/mixdb-context/save-many": {
      "post": {
        "tags": [
          "Portal - mix Database Context"
        ],
        "requestBody": {
          "content": {
            "application/json-patch+json": {
              "schema": {
                "type": "array",
                "items": {
                  "$ref": "#/components/schemas/Mix.Lib.ViewModels.MixDatabaseContextViewModel"
                }
              }
            },
            "application/json": {
              "schema": {
                "type": "array",
                "items": {
                  "$ref": "#/components/schemas/Mix.Lib.ViewModels.MixDatabaseContextViewModel"
                }
              }
            },
            "text/json": {
              "schema": {
                "type": "array",
                "items": {
                  "$ref": "#/components/schemas/Mix.Lib.ViewModels.MixDatabaseContextViewModel"
                }
              }
            },
            "application/*+json": {
              "schema": {
                "type": "array",
                "items": {
                  "$ref": "#/components/schemas/Mix.Lib.ViewModels.MixDatabaseContextViewModel"
                }
              }
            }
          }
        },
        "responses": {
          "200": {
            "description": "OK"
          }
        }
      }
    },
    "/api/v2/rest/mix-portal/mixdb-context/filter": {
      "post": {
        "tags": [
          "Portal - mix Database Context"
        ],
        "requestBody": {
          "content": {
            "application/json-patch+json": {
              "schema": {
                "$ref": "#/components/schemas/Mix.Shared.Dtos.SearchRequestDto"
              }
            },
            "application/json": {
              "schema": {
                "$ref": "#/components/schemas/Mix.Shared.Dtos.SearchRequestDto"
              }
            },
            "text/json": {
              "schema": {
                "$ref": "#/components/schemas/Mix.Shared.Dtos.SearchRequestDto"
              }
            },
            "application/*+json": {
              "schema": {
                "$ref": "#/components/schemas/Mix.Shared.Dtos.SearchRequestDto"
              }
            }
          }
        },
        "responses": {
          "200": {
            "description": "OK",
            "content": {
              "text/plain": {
                "schema": {
                  "$ref": "#/components/schemas/Mix.Heart.Models.PagingResponseModel`1[[Mix.Lib.ViewModels.MixDatabaseContextViewModel, mix.library, Version=1.0.0.0, Culture=neutral, PublicKeyToken=null]]"
                }
              },
              "application/json": {
                "schema": {
                  "$ref": "#/components/schemas/Mix.Heart.Models.PagingResponseModel`1[[Mix.Lib.ViewModels.MixDatabaseContextViewModel, mix.library, Version=1.0.0.0, Culture=neutral, PublicKeyToken=null]]"
                }
              },
              "text/json": {
                "schema": {
                  "$ref": "#/components/schemas/Mix.Heart.Models.PagingResponseModel`1[[Mix.Lib.ViewModels.MixDatabaseContextViewModel, mix.library, Version=1.0.0.0, Culture=neutral, PublicKeyToken=null]]"
                }
              }
            }
          }
        }
      }
    },
    "/api/v2/rest/mix-portal/mixdb-context/default": {
      "get": {
        "tags": [
          "Portal - mix Database Context"
        ],
        "responses": {
          "200": {
            "description": "OK",
            "content": {
              "text/plain": {
                "schema": {
                  "$ref": "#/components/schemas/Mix.Lib.ViewModels.MixDatabaseContextViewModel"
                }
              },
              "application/json": {
                "schema": {
                  "$ref": "#/components/schemas/Mix.Lib.ViewModels.MixDatabaseContextViewModel"
                }
              },
              "text/json": {
                "schema": {
                  "$ref": "#/components/schemas/Mix.Lib.ViewModels.MixDatabaseContextViewModel"
                }
              }
            }
          }
        }
      }
    },
    "/api/v2/rest/mix-portal/mix-database-relationship": {
      "post": {
        "tags": [
          "Portal - mix Database Relationship"
        ],
        "requestBody": {
          "content": {
            "application/json-patch+json": {
              "schema": {
                "$ref": "#/components/schemas/Mix.Lib.ViewModels.MixDatabaseRelationshipViewModel"
              }
            },
            "application/json": {
              "schema": {
                "$ref": "#/components/schemas/Mix.Lib.ViewModels.MixDatabaseRelationshipViewModel"
              }
            },
            "text/json": {
              "schema": {
                "$ref": "#/components/schemas/Mix.Lib.ViewModels.MixDatabaseRelationshipViewModel"
              }
            },
            "application/*+json": {
              "schema": {
                "$ref": "#/components/schemas/Mix.Lib.ViewModels.MixDatabaseRelationshipViewModel"
              }
            }
          }
        },
        "responses": {
          "200": {
            "description": "OK",
            "content": {
              "text/plain": {
                "schema": {
                  "$ref": "#/components/schemas/Mix.Lib.ViewModels.MixDatabaseRelationshipViewModel"
                }
              },
              "application/json": {
                "schema": {
                  "$ref": "#/components/schemas/Mix.Lib.ViewModels.MixDatabaseRelationshipViewModel"
                }
              },
              "text/json": {
                "schema": {
                  "$ref": "#/components/schemas/Mix.Lib.ViewModels.MixDatabaseRelationshipViewModel"
                }
              }
            }
          }
        }
      },
      "patch": {
        "tags": [
          "Portal - mix Database Relationship"
        ],
        "requestBody": {
          "content": {
            "application/json-patch+json": {
              "schema": {
                "type": "object",
                "additionalProperties": {
                  "$ref": "#/components/schemas/Newtonsoft.Json.Linq.JToken"
                }
              }
            },
            "application/json": {
              "schema": {
                "type": "object",
                "additionalProperties": {
                  "$ref": "#/components/schemas/Newtonsoft.Json.Linq.JToken"
                }
              }
            },
            "text/json": {
              "schema": {
                "type": "object",
                "additionalProperties": {
                  "$ref": "#/components/schemas/Newtonsoft.Json.Linq.JToken"
                }
              }
            },
            "application/*+json": {
              "schema": {
                "type": "object",
                "additionalProperties": {
                  "$ref": "#/components/schemas/Newtonsoft.Json.Linq.JToken"
                }
              }
            }
          }
        },
        "responses": {
          "200": {
            "description": "OK"
          }
        }
      },
      "get": {
        "tags": [
          "Portal - mix Database Relationship"
        ],
        "parameters": [
          {
            "name": "LoadNestedData",
            "in": "query",
            "schema": {
              "type": "boolean"
            }
          },
          {
            "name": "MixDatabaseName",
            "in": "query",
            "schema": {
              "type": "string"
            }
          },
          {
            "name": "Keyword",
            "in": "query",
            "schema": {
              "type": "string"
            }
          },
          {
            "name": "Culture",
            "in": "query",
            "schema": {
              "type": "string"
            }
          },
          {
            "name": "FromDate",
            "in": "query",
            "schema": {
              "type": "string",
              "format": "date-time"
            }
          },
          {
            "name": "ToDate",
            "in": "query",
            "schema": {
              "type": "string",
              "format": "date-time"
            }
          },
          {
            "name": "PageIndex",
            "in": "query",
            "schema": {
              "type": "integer",
              "format": "int32"
            }
          },
          {
            "name": "PageSize",
            "in": "query",
            "schema": {
              "type": "integer",
              "format": "int32"
            }
          },
          {
            "name": "PagingState",
            "in": "query",
            "schema": {
              "type": "string"
            }
          },
          {
            "name": "SortBy",
            "in": "query",
            "schema": {
              "type": "string"
            }
          },
          {
            "name": "OrderBy",
            "in": "query",
            "schema": {
              "type": "string"
            }
          },
          {
            "name": "Conjunction",
            "in": "query",
            "schema": {
              "$ref": "#/components/schemas/Mix.Constant.Enums.MixConjunction"
            }
          },
          {
            "name": "Direction",
            "in": "query",
            "schema": {
              "$ref": "#/components/schemas/Mix.Heart.Enums.SortDirection"
            }
          },
          {
            "name": "Status",
            "in": "query",
            "schema": {
              "$ref": "#/components/schemas/Mix.Heart.Enums.MixContentStatus"
            }
          },
          {
            "name": "SearchMethod",
            "in": "query",
            "schema": {
              "$ref": "#/components/schemas/Mix.Constant.Enums.MixCompareOperator"
            }
          },
          {
            "name": "Columns",
            "in": "query",
            "schema": {
              "type": "string"
            }
          },
          {
            "name": "SearchColumns",
            "in": "query",
            "schema": {
              "type": "string"
            }
          },
          {
            "name": "After",
            "in": "query",
            "schema": {}
          },
          {
            "name": "Before",
            "in": "query",
            "schema": {}
          },
          {
            "name": "Queries",
            "in": "query",
            "schema": {
              "type": "array",
              "items": {
                "$ref": "#/components/schemas/Mix.Shared.Dtos.MixQueryField"
              }
            }
          },
          {
            "name": "SortByFields",
            "in": "query",
            "schema": {
              "type": "array",
              "items": {
                "$ref": "#/components/schemas/Mix.Heart.Model.MixSortByColumn"
              }
            }
          }
        ],
        "responses": {
          "200": {
            "description": "OK",
            "content": {
              "text/plain": {
                "schema": {
                  "$ref": "#/components/schemas/Mix.Heart.Models.PagingResponseModel`1[[Mix.Lib.ViewModels.MixDatabaseRelationshipViewModel, mix.library, Version=1.0.0.0, Culture=neutral, PublicKeyToken=null]]"
                }
              },
              "application/json": {
                "schema": {
                  "$ref": "#/components/schemas/Mix.Heart.Models.PagingResponseModel`1[[Mix.Lib.ViewModels.MixDatabaseRelationshipViewModel, mix.library, Version=1.0.0.0, Culture=neutral, PublicKeyToken=null]]"
                }
              },
              "text/json": {
                "schema": {
                  "$ref": "#/components/schemas/Mix.Heart.Models.PagingResponseModel`1[[Mix.Lib.ViewModels.MixDatabaseRelationshipViewModel, mix.library, Version=1.0.0.0, Culture=neutral, PublicKeyToken=null]]"
                }
              }
            }
          }
        }
      }
    },
    "/api/v2/rest/mix-portal/mix-database-relationship/{id}": {
      "put": {
        "tags": [
          "Portal - mix Database Relationship"
        ],
        "parameters": [
          {
            "name": "id",
            "in": "path",
            "required": true,
            "schema": {
              "type": "integer",
              "format": "int32"
            }
          }
        ],
        "requestBody": {
          "content": {
            "application/json-patch+json": {
              "schema": {
                "$ref": "#/components/schemas/Mix.Lib.ViewModels.MixDatabaseRelationshipViewModel"
              }
            },
            "application/json": {
              "schema": {
                "$ref": "#/components/schemas/Mix.Lib.ViewModels.MixDatabaseRelationshipViewModel"
              }
            },
            "text/json": {
              "schema": {
                "$ref": "#/components/schemas/Mix.Lib.ViewModels.MixDatabaseRelationshipViewModel"
              }
            },
            "application/*+json": {
              "schema": {
                "$ref": "#/components/schemas/Mix.Lib.ViewModels.MixDatabaseRelationshipViewModel"
              }
            }
          }
        },
        "responses": {
          "200": {
            "description": "OK"
          }
        }
      },
      "delete": {
        "tags": [
          "Portal - mix Database Relationship"
        ],
        "parameters": [
          {
            "name": "id",
            "in": "path",
            "required": true,
            "schema": {
              "type": "integer",
              "format": "int32"
            }
          }
        ],
        "responses": {
          "200": {
            "description": "OK"
          }
        }
      },
      "get": {
        "tags": [
          "Portal - mix Database Relationship"
        ],
        "parameters": [
          {
            "name": "id",
            "in": "path",
            "required": true,
            "schema": {
              "type": "integer",
              "format": "int32"
            }
          }
        ],
        "responses": {
          "200": {
            "description": "OK",
            "content": {
              "text/plain": {
                "schema": {
                  "$ref": "#/components/schemas/Mix.Lib.ViewModels.MixDatabaseRelationshipViewModel"
                }
              },
              "application/json": {
                "schema": {
                  "$ref": "#/components/schemas/Mix.Lib.ViewModels.MixDatabaseRelationshipViewModel"
                }
              },
              "text/json": {
                "schema": {
                  "$ref": "#/components/schemas/Mix.Lib.ViewModels.MixDatabaseRelationshipViewModel"
                }
              }
            }
          }
        }
      }
    },
    "/api/v2/rest/mix-portal/mix-database-relationship/remove-cache/{id}": {
      "delete": {
        "tags": [
          "Portal - mix Database Relationship"
        ],
        "parameters": [
          {
            "name": "id",
            "in": "path",
            "required": true,
            "schema": {
              "type": "integer",
              "format": "int32"
            }
          }
        ],
        "responses": {
          "200": {
            "description": "OK"
          }
        }
      }
    },
    "/api/v2/rest/mix-portal/mix-database-relationship/patch-many": {
      "patch": {
        "tags": [
          "Portal - mix Database Relationship"
        ],
        "requestBody": {
          "content": {
            "application/json-patch+json": {
              "schema": {
                "type": "array",
                "items": {
                  "type": "object",
                  "additionalProperties": {
                    "$ref": "#/components/schemas/Newtonsoft.Json.Linq.JToken"
                  }
                }
              }
            },
            "application/json": {
              "schema": {
                "type": "array",
                "items": {
                  "type": "object",
                  "additionalProperties": {
                    "$ref": "#/components/schemas/Newtonsoft.Json.Linq.JToken"
                  }
                }
              }
            },
            "text/json": {
              "schema": {
                "type": "array",
                "items": {
                  "type": "object",
                  "additionalProperties": {
                    "$ref": "#/components/schemas/Newtonsoft.Json.Linq.JToken"
                  }
                }
              }
            },
            "application/*+json": {
              "schema": {
                "type": "array",
                "items": {
                  "type": "object",
                  "additionalProperties": {
                    "$ref": "#/components/schemas/Newtonsoft.Json.Linq.JToken"
                  }
                }
              }
            }
          }
        },
        "responses": {
          "200": {
            "description": "OK"
          }
        }
      }
    },
    "/api/v2/rest/mix-portal/mix-database-relationship/save-many": {
      "post": {
        "tags": [
          "Portal - mix Database Relationship"
        ],
        "requestBody": {
          "content": {
            "application/json-patch+json": {
              "schema": {
                "type": "array",
                "items": {
                  "$ref": "#/components/schemas/Mix.Lib.ViewModels.MixDatabaseRelationshipViewModel"
                }
              }
            },
            "application/json": {
              "schema": {
                "type": "array",
                "items": {
                  "$ref": "#/components/schemas/Mix.Lib.ViewModels.MixDatabaseRelationshipViewModel"
                }
              }
            },
            "text/json": {
              "schema": {
                "type": "array",
                "items": {
                  "$ref": "#/components/schemas/Mix.Lib.ViewModels.MixDatabaseRelationshipViewModel"
                }
              }
            },
            "application/*+json": {
              "schema": {
                "type": "array",
                "items": {
                  "$ref": "#/components/schemas/Mix.Lib.ViewModels.MixDatabaseRelationshipViewModel"
                }
              }
            }
          }
        },
        "responses": {
          "200": {
            "description": "OK"
          }
        }
      }
    },
    "/api/v2/rest/mix-portal/mix-database-relationship/filter": {
      "post": {
        "tags": [
          "Portal - mix Database Relationship"
        ],
        "requestBody": {
          "content": {
            "application/json-patch+json": {
              "schema": {
                "$ref": "#/components/schemas/Mix.Shared.Dtos.SearchRequestDto"
              }
            },
            "application/json": {
              "schema": {
                "$ref": "#/components/schemas/Mix.Shared.Dtos.SearchRequestDto"
              }
            },
            "text/json": {
              "schema": {
                "$ref": "#/components/schemas/Mix.Shared.Dtos.SearchRequestDto"
              }
            },
            "application/*+json": {
              "schema": {
                "$ref": "#/components/schemas/Mix.Shared.Dtos.SearchRequestDto"
              }
            }
          }
        },
        "responses": {
          "200": {
            "description": "OK",
            "content": {
              "text/plain": {
                "schema": {
                  "$ref": "#/components/schemas/Mix.Heart.Models.PagingResponseModel`1[[Mix.Lib.ViewModels.MixDatabaseRelationshipViewModel, mix.library, Version=1.0.0.0, Culture=neutral, PublicKeyToken=null]]"
                }
              },
              "application/json": {
                "schema": {
                  "$ref": "#/components/schemas/Mix.Heart.Models.PagingResponseModel`1[[Mix.Lib.ViewModels.MixDatabaseRelationshipViewModel, mix.library, Version=1.0.0.0, Culture=neutral, PublicKeyToken=null]]"
                }
              },
              "text/json": {
                "schema": {
                  "$ref": "#/components/schemas/Mix.Heart.Models.PagingResponseModel`1[[Mix.Lib.ViewModels.MixDatabaseRelationshipViewModel, mix.library, Version=1.0.0.0, Culture=neutral, PublicKeyToken=null]]"
                }
              }
            }
          }
        }
      }
    },
    "/api/v2/rest/mix-portal/mix-database-relationship/default": {
      "get": {
        "tags": [
          "Portal - mix Database Relationship"
        ],
        "responses": {
          "200": {
            "description": "OK",
            "content": {
              "text/plain": {
                "schema": {
                  "$ref": "#/components/schemas/Mix.Lib.ViewModels.MixDatabaseRelationshipViewModel"
                }
              },
              "application/json": {
                "schema": {
                  "$ref": "#/components/schemas/Mix.Lib.ViewModels.MixDatabaseRelationshipViewModel"
                }
              },
              "text/json": {
                "schema": {
                  "$ref": "#/components/schemas/Mix.Lib.ViewModels.MixDatabaseRelationshipViewModel"
                }
              }
            }
          }
        }
      }
    },
    "/api/v2/rest/mix-portal/mix-db/{name}/by-ids": {
      "post": {
        "tags": [
          "Portal - mix Db"
        ],
        "parameters": [
          {
            "name": "name",
            "in": "path",
            "required": true,
            "schema": {
              "type": "string"
            }
          }
        ],
        "requestBody": {
          "content": {
            "application/json-patch+json": {
              "schema": {
                "$ref": "#/components/schemas/Mix.Shared.Dtos.GetIdsDto"
              }
            },
            "application/json": {
              "schema": {
                "$ref": "#/components/schemas/Mix.Shared.Dtos.GetIdsDto"
              }
            },
            "text/json": {
              "schema": {
                "$ref": "#/components/schemas/Mix.Shared.Dtos.GetIdsDto"
              }
            },
            "application/*+json": {
              "schema": {
                "$ref": "#/components/schemas/Mix.Shared.Dtos.GetIdsDto"
              }
            }
          }
        },
        "responses": {
          "200": {
            "description": "OK",
            "content": {
              "text/plain": {
                "schema": {
                  "$ref": "#/components/schemas/Mix.Heart.Models.PagingResponseModel`1[[Newtonsoft.Json.Linq.JObject, Newtonsoft.Json, Version=13.0.0.0, Culture=neutral, PublicKeyToken=30ad4fe6b2a6aeed]]"
                }
              },
              "application/json": {
                "schema": {
                  "$ref": "#/components/schemas/Mix.Heart.Models.PagingResponseModel`1[[Newtonsoft.Json.Linq.JObject, Newtonsoft.Json, Version=13.0.0.0, Culture=neutral, PublicKeyToken=30ad4fe6b2a6aeed]]"
                }
              },
              "text/json": {
                "schema": {
                  "$ref": "#/components/schemas/Mix.Heart.Models.PagingResponseModel`1[[Newtonsoft.Json.Linq.JObject, Newtonsoft.Json, Version=13.0.0.0, Culture=neutral, PublicKeyToken=30ad4fe6b2a6aeed]]"
                }
              }
            }
          }
        }
      }
    },
    "/api/v2/rest/mix-portal/mix-db/{name}/filter": {
      "post": {
        "tags": [
          "Portal - mix Db"
        ],
        "parameters": [
          {
            "name": "name",
            "in": "path",
            "required": true,
            "schema": {
              "type": "string"
            }
          }
        ],
        "requestBody": {
          "content": {
            "application/json-patch+json": {
              "schema": {
                "$ref": "#/components/schemas/Mix.Shared.Dtos.SearchMixDbRequestDto"
              }
            },
            "application/json": {
              "schema": {
                "$ref": "#/components/schemas/Mix.Shared.Dtos.SearchMixDbRequestDto"
              }
            },
            "text/json": {
              "schema": {
                "$ref": "#/components/schemas/Mix.Shared.Dtos.SearchMixDbRequestDto"
              }
            },
            "application/*+json": {
              "schema": {
                "$ref": "#/components/schemas/Mix.Shared.Dtos.SearchMixDbRequestDto"
              }
            }
          }
        },
        "responses": {
          "200": {
            "description": "OK",
            "content": {
              "text/plain": {
                "schema": {
                  "$ref": "#/components/schemas/Mix.Heart.Models.PagingResponseModel`1[[Newtonsoft.Json.Linq.JObject, Newtonsoft.Json, Version=13.0.0.0, Culture=neutral, PublicKeyToken=30ad4fe6b2a6aeed]]"
                }
              },
              "application/json": {
                "schema": {
                  "$ref": "#/components/schemas/Mix.Heart.Models.PagingResponseModel`1[[Newtonsoft.Json.Linq.JObject, Newtonsoft.Json, Version=13.0.0.0, Culture=neutral, PublicKeyToken=30ad4fe6b2a6aeed]]"
                }
              },
              "text/json": {
                "schema": {
                  "$ref": "#/components/schemas/Mix.Heart.Models.PagingResponseModel`1[[Newtonsoft.Json.Linq.JObject, Newtonsoft.Json, Version=13.0.0.0, Culture=neutral, PublicKeyToken=30ad4fe6b2a6aeed]]"
                }
              }
            }
          }
        }
      }
    },
    "/api/v2/rest/mix-portal/mix-db/{name}/nested-data/filter": {
      "post": {
        "tags": [
          "Portal - mix Db"
        ],
        "parameters": [
          {
            "name": "name",
            "in": "path",
            "required": true,
            "schema": {
              "type": "string"
            }
          }
        ],
        "requestBody": {
          "content": {
            "application/json-patch+json": {
              "schema": {
                "$ref": "#/components/schemas/Mix.Shared.Dtos.SearchMixDbRequestDto"
              }
            },
            "application/json": {
              "schema": {
                "$ref": "#/components/schemas/Mix.Shared.Dtos.SearchMixDbRequestDto"
              }
            },
            "text/json": {
              "schema": {
                "$ref": "#/components/schemas/Mix.Shared.Dtos.SearchMixDbRequestDto"
              }
            },
            "application/*+json": {
              "schema": {
                "$ref": "#/components/schemas/Mix.Shared.Dtos.SearchMixDbRequestDto"
              }
            }
          }
        },
        "responses": {
          "200": {
            "description": "OK",
            "content": {
              "text/plain": {
                "schema": {
                  "$ref": "#/components/schemas/Mix.Heart.Models.PagingResponseModel`1[[Newtonsoft.Json.Linq.JObject, Newtonsoft.Json, Version=13.0.0.0, Culture=neutral, PublicKeyToken=30ad4fe6b2a6aeed]]"
                }
              },
              "application/json": {
                "schema": {
                  "$ref": "#/components/schemas/Mix.Heart.Models.PagingResponseModel`1[[Newtonsoft.Json.Linq.JObject, Newtonsoft.Json, Version=13.0.0.0, Culture=neutral, PublicKeyToken=30ad4fe6b2a6aeed]]"
                }
              },
              "text/json": {
                "schema": {
                  "$ref": "#/components/schemas/Mix.Heart.Models.PagingResponseModel`1[[Newtonsoft.Json.Linq.JObject, Newtonsoft.Json, Version=13.0.0.0, Culture=neutral, PublicKeyToken=30ad4fe6b2a6aeed]]"
                }
              }
            }
          }
        }
      }
    },
    "/api/v2/rest/mix-portal/mix-db/{name}/export": {
      "post": {
        "tags": [
          "Portal - mix Db"
        ],
        "parameters": [
          {
            "name": "name",
            "in": "path",
            "required": true,
            "schema": {
              "type": "string"
            }
          }
        ],
        "requestBody": {
          "content": {
            "application/json-patch+json": {
              "schema": {
                "$ref": "#/components/schemas/Mix.Shared.Dtos.SearchMixDbRequestDto"
              }
            },
            "application/json": {
              "schema": {
                "$ref": "#/components/schemas/Mix.Shared.Dtos.SearchMixDbRequestDto"
              }
            },
            "text/json": {
              "schema": {
                "$ref": "#/components/schemas/Mix.Shared.Dtos.SearchMixDbRequestDto"
              }
            },
            "application/*+json": {
              "schema": {
                "$ref": "#/components/schemas/Mix.Shared.Dtos.SearchMixDbRequestDto"
              }
            }
          }
        },
        "responses": {
          "200": {
            "description": "OK",
            "content": {
              "text/plain": {
                "schema": {
                  "$ref": "#/components/schemas/Mix.Heart.Models.FileModel"
                }
              },
              "application/json": {
                "schema": {
                  "$ref": "#/components/schemas/Mix.Heart.Models.FileModel"
                }
              },
              "text/json": {
                "schema": {
                  "$ref": "#/components/schemas/Mix.Heart.Models.FileModel"
                }
              }
            }
          }
        }
      }
    },
    "/api/v2/rest/mix-portal/mix-db/{name}/import": {
      "post": {
        "tags": [
          "Portal - mix Db"
        ],
        "parameters": [
          {
            "name": "name",
            "in": "path",
            "required": true,
            "schema": {
              "type": "string"
            }
          }
        ],
        "requestBody": {
          "content": {
            "multipart/form-data": {
              "schema": {
                "type": "object",
                "properties": {
                  "file": {
                    "type": "string",
                    "format": "binary"
                  }
                }
              },
              "encoding": {
                "file": {
                  "style": "form"
                }
              }
            }
          }
        },
        "responses": {
          "200": {
            "description": "OK"
          }
        }
      }
    },
    "/api/v2/rest/mix-portal/mix-db/{name}/{id}": {
      "get": {
        "tags": [
          "Portal - mix Db"
        ],
        "parameters": [
          {
            "name": "id",
            "in": "path",
            "required": true,
            "schema": {
              "type": "string"
            }
          },
          {
            "name": "selectColumns",
            "in": "query",
            "schema": {
              "type": "string"
            }
          },
          {
            "name": "name",
            "in": "path",
            "required": true,
            "schema": {
              "type": "string"
            }
          }
        ],
        "responses": {
          "200": {
            "description": "OK",
            "content": {
              "text/plain": {
                "schema": {
                  "type": "object",
                  "additionalProperties": {
                    "$ref": "#/components/schemas/Newtonsoft.Json.Linq.JToken"
                  }
                }
              },
              "application/json": {
                "schema": {
                  "type": "object",
                  "additionalProperties": {
                    "$ref": "#/components/schemas/Newtonsoft.Json.Linq.JToken"
                  }
                }
              },
              "text/json": {
                "schema": {
                  "type": "object",
                  "additionalProperties": {
                    "$ref": "#/components/schemas/Newtonsoft.Json.Linq.JToken"
                  }
                }
              }
            }
          }
        }
      },
      "put": {
        "tags": [
          "Portal - mix Db"
        ],
        "parameters": [
          {
            "name": "id",
            "in": "path",
            "required": true,
            "schema": {
              "type": "string"
            }
          },
          {
            "name": "name",
            "in": "path",
            "required": true,
            "schema": {
              "type": "string"
            }
          }
        ],
        "requestBody": {
          "content": {
            "application/json-patch+json": {
              "schema": {
                "type": "object",
                "additionalProperties": {
                  "$ref": "#/components/schemas/Newtonsoft.Json.Linq.JToken"
                }
              }
            },
            "application/json": {
              "schema": {
                "type": "object",
                "additionalProperties": {
                  "$ref": "#/components/schemas/Newtonsoft.Json.Linq.JToken"
                }
              }
            },
            "text/json": {
              "schema": {
                "type": "object",
                "additionalProperties": {
                  "$ref": "#/components/schemas/Newtonsoft.Json.Linq.JToken"
                }
              }
            },
            "application/*+json": {
              "schema": {
                "type": "object",
                "additionalProperties": {
                  "$ref": "#/components/schemas/Newtonsoft.Json.Linq.JToken"
                }
              }
            }
          }
        },
        "responses": {
          "200": {
            "description": "OK"
          }
        }
      },
      "delete": {
        "tags": [
          "Portal - mix Db"
        ],
        "parameters": [
          {
            "name": "id",
            "in": "path",
            "required": true,
            "schema": {
              "type": "string"
            }
          },
          {
            "name": "name",
            "in": "path",
            "required": true,
            "schema": {
              "type": "string"
            }
          }
        ],
        "responses": {
          "200": {
            "description": "OK"
          }
        }
      }
    },
    "/api/v2/rest/mix-portal/mix-db/{name}/get-by-parent/{parentType}/{parentId}": {
      "get": {
        "tags": [
          "Portal - mix Db"
        ],
        "parameters": [
          {
            "name": "parentType",
            "in": "path",
            "required": true,
            "schema": {
              "$ref": "#/components/schemas/Mix.Constant.Enums.MixContentType"
            }
          },
          {
            "name": "parentId",
            "in": "path",
            "required": true,
            "schema": {
              "type": "integer",
              "format": "int32"
            }
          },
          {
            "name": "selectColumns",
            "in": "query",
            "schema": {
              "type": "string"
            }
          },
          {
            "name": "name",
            "in": "path",
            "required": true,
            "schema": {
              "type": "string"
            }
          }
        ],
        "responses": {
          "200": {
            "description": "OK",
            "content": {
              "text/plain": {
                "schema": {
                  "type": "object",
                  "additionalProperties": {
                    "$ref": "#/components/schemas/Newtonsoft.Json.Linq.JToken"
                  }
                }
              },
              "application/json": {
                "schema": {
                  "type": "object",
                  "additionalProperties": {
                    "$ref": "#/components/schemas/Newtonsoft.Json.Linq.JToken"
                  }
                }
              },
              "text/json": {
                "schema": {
                  "type": "object",
                  "additionalProperties": {
                    "$ref": "#/components/schemas/Newtonsoft.Json.Linq.JToken"
                  }
                }
              }
            }
          }
        }
      }
    },
    "/api/v2/rest/mix-portal/mix-db/{name}/get-by-guid-parent/{parentType}/{parentId}": {
      "get": {
        "tags": [
          "Portal - mix Db"
        ],
        "parameters": [
          {
            "name": "parentType",
            "in": "path",
            "required": true,
            "schema": {
              "$ref": "#/components/schemas/Mix.Constant.Enums.MixContentType"
            }
          },
          {
            "name": "parentId",
            "in": "path",
            "required": true,
            "schema": {
              "type": "string",
              "format": "uuid"
            }
          },
          {
            "name": "selectColumns",
            "in": "query",
            "schema": {
              "type": "string"
            }
          },
          {
            "name": "name",
            "in": "path",
            "required": true,
            "schema": {
              "type": "string"
            }
          }
        ],
        "responses": {
          "200": {
            "description": "OK",
            "content": {
              "text/plain": {
                "schema": {
                  "type": "object",
                  "additionalProperties": {
                    "$ref": "#/components/schemas/Newtonsoft.Json.Linq.JToken"
                  }
                }
              },
              "application/json": {
                "schema": {
                  "type": "object",
                  "additionalProperties": {
                    "$ref": "#/components/schemas/Newtonsoft.Json.Linq.JToken"
                  }
                }
              },
              "text/json": {
                "schema": {
                  "type": "object",
                  "additionalProperties": {
                    "$ref": "#/components/schemas/Newtonsoft.Json.Linq.JToken"
                  }
                }
              }
            }
          }
        }
      }
    },
    "/api/v2/rest/mix-portal/mix-db/{name}/hub": {
      "post": {
        "tags": [
          "Portal - mix Db"
        ],
        "parameters": [
          {
            "name": "name",
            "in": "path",
            "required": true,
            "schema": {
              "type": "string"
            }
          }
        ],
        "requestBody": {
          "content": {
            "application/json-patch+json": {
              "schema": {}
            },
            "application/json": {
              "schema": {}
            },
            "text/json": {
              "schema": {}
            },
            "application/*+json": {
              "schema": {}
            }
          }
        },
        "responses": {
          "200": {
            "description": "OK"
          }
        }
      }
    },
    "/api/v2/rest/mix-portal/mix-db/{name}": {
      "post": {
        "tags": [
          "Portal - mix Db"
        ],
        "parameters": [
          {
            "name": "name",
            "in": "path",
            "required": true,
            "schema": {
              "type": "string"
            }
          }
        ],
        "requestBody": {
          "content": {
            "application/json-patch+json": {
              "schema": {
                "type": "object",
                "additionalProperties": {
                  "$ref": "#/components/schemas/Newtonsoft.Json.Linq.JToken"
                }
              }
            },
            "application/json": {
              "schema": {
                "type": "object",
                "additionalProperties": {
                  "$ref": "#/components/schemas/Newtonsoft.Json.Linq.JToken"
                }
              }
            },
            "text/json": {
              "schema": {
                "type": "object",
                "additionalProperties": {
                  "$ref": "#/components/schemas/Newtonsoft.Json.Linq.JToken"
                }
              }
            },
            "application/*+json": {
              "schema": {
                "type": "object",
                "additionalProperties": {
                  "$ref": "#/components/schemas/Newtonsoft.Json.Linq.JToken"
                }
              }
            }
          }
        },
        "responses": {
          "200": {
            "description": "OK"
          }
        }
      },
      "patch": {
        "tags": [
          "Portal - mix Db"
        ],
        "parameters": [
          {
            "name": "name",
            "in": "path",
            "required": true,
            "schema": {
              "type": "string"
            }
          }
        ],
        "requestBody": {
          "content": {
            "application/json-patch+json": {
              "schema": {
                "type": "object",
                "additionalProperties": {
                  "$ref": "#/components/schemas/Newtonsoft.Json.Linq.JToken"
                }
              }
            },
            "application/json": {
              "schema": {
                "type": "object",
                "additionalProperties": {
                  "$ref": "#/components/schemas/Newtonsoft.Json.Linq.JToken"
                }
              }
            },
            "text/json": {
              "schema": {
                "type": "object",
                "additionalProperties": {
                  "$ref": "#/components/schemas/Newtonsoft.Json.Linq.JToken"
                }
              }
            },
            "application/*+json": {
              "schema": {
                "type": "object",
                "additionalProperties": {
                  "$ref": "#/components/schemas/Newtonsoft.Json.Linq.JToken"
                }
              }
            }
          }
        },
        "responses": {
          "200": {
            "description": "OK",
            "content": {
              "text/plain": {
                "schema": {
                  "type": "object",
                  "additionalProperties": {
                    "$ref": "#/components/schemas/Newtonsoft.Json.Linq.JToken"
                  }
                }
              },
              "application/json": {
                "schema": {
                  "type": "object",
                  "additionalProperties": {
                    "$ref": "#/components/schemas/Newtonsoft.Json.Linq.JToken"
                  }
                }
              },
              "text/json": {
                "schema": {
                  "type": "object",
                  "additionalProperties": {
                    "$ref": "#/components/schemas/Newtonsoft.Json.Linq.JToken"
                  }
                }
              }
            }
          }
        }
      }
    },
    "/api/v2/rest/mix-portal/mix-db/{name}/data-relationship": {
      "post": {
        "tags": [
          "Portal - mix Db"
        ],
        "parameters": [
          {
            "name": "name",
            "in": "path",
            "required": true,
            "schema": {
              "type": "string"
            }
          }
        ],
        "requestBody": {
          "content": {
            "application/json-patch+json": {
              "schema": {
                "$ref": "#/components/schemas/Mix.Mixdb.Dtos.CreateDataRelationshipDto"
              }
            },
            "application/json": {
              "schema": {
                "$ref": "#/components/schemas/Mix.Mixdb.Dtos.CreateDataRelationshipDto"
              }
            },
            "text/json": {
              "schema": {
                "$ref": "#/components/schemas/Mix.Mixdb.Dtos.CreateDataRelationshipDto"
              }
            },
            "application/*+json": {
              "schema": {
                "$ref": "#/components/schemas/Mix.Mixdb.Dtos.CreateDataRelationshipDto"
              }
            }
          }
        },
        "responses": {
          "200": {
            "description": "OK"
          }
        }
      }
    },
    "/api/v2/rest/mix-portal/mix-db/{name}/data-relationship/{id}": {
      "delete": {
        "tags": [
          "Portal - mix Db"
        ],
        "parameters": [
          {
            "name": "id",
            "in": "path",
            "required": true,
            "schema": {
              "type": "integer",
              "format": "int32"
            }
          },
          {
            "name": "name",
            "in": "path",
            "required": true,
            "schema": {
              "type": "string"
            }
          }
        ],
        "responses": {
          "200": {
            "description": "OK"
          }
        }
      }
    },
    "/api/v2/rest/mix-portal/mix-db/{name}/patch-many": {
      "patch": {
        "tags": [
          "Portal - mix Db"
        ],
        "parameters": [
          {
            "name": "name",
            "in": "path",
            "required": true,
            "schema": {
              "type": "string"
            }
          }
        ],
        "requestBody": {
          "content": {
            "application/json-patch+json": {
              "schema": {
                "type": "array",
                "items": {
                  "type": "object",
                  "additionalProperties": {
                    "$ref": "#/components/schemas/Newtonsoft.Json.Linq.JToken"
                  }
                }
              }
            },
            "application/json": {
              "schema": {
                "type": "array",
                "items": {
                  "type": "object",
                  "additionalProperties": {
                    "$ref": "#/components/schemas/Newtonsoft.Json.Linq.JToken"
                  }
                }
              }
            },
            "text/json": {
              "schema": {
                "type": "array",
                "items": {
                  "type": "object",
                  "additionalProperties": {
                    "$ref": "#/components/schemas/Newtonsoft.Json.Linq.JToken"
                  }
                }
              }
            },
            "application/*+json": {
              "schema": {
                "type": "array",
                "items": {
                  "type": "object",
                  "additionalProperties": {
                    "$ref": "#/components/schemas/Newtonsoft.Json.Linq.JToken"
                  }
                }
              }
            }
          }
        },
        "responses": {
          "200": {
            "description": "OK"
          }
        }
      }
    },
    "/api/v2/rest/mix-portal/mix-domain": {
      "post": {
        "tags": [
          "Portal - mix Domain"
        ],
        "requestBody": {
          "content": {
            "application/json-patch+json": {
              "schema": {
                "$ref": "#/components/schemas/Mix.Lib.ViewModels.MixDomainViewModel"
              }
            },
            "application/json": {
              "schema": {
                "$ref": "#/components/schemas/Mix.Lib.ViewModels.MixDomainViewModel"
              }
            },
            "text/json": {
              "schema": {
                "$ref": "#/components/schemas/Mix.Lib.ViewModels.MixDomainViewModel"
              }
            },
            "application/*+json": {
              "schema": {
                "$ref": "#/components/schemas/Mix.Lib.ViewModels.MixDomainViewModel"
              }
            }
          }
        },
        "responses": {
          "200": {
            "description": "OK",
            "content": {
              "text/plain": {
                "schema": {
                  "$ref": "#/components/schemas/Mix.Lib.ViewModels.MixDomainViewModel"
                }
              },
              "application/json": {
                "schema": {
                  "$ref": "#/components/schemas/Mix.Lib.ViewModels.MixDomainViewModel"
                }
              },
              "text/json": {
                "schema": {
                  "$ref": "#/components/schemas/Mix.Lib.ViewModels.MixDomainViewModel"
                }
              }
            }
          }
        }
      },
      "patch": {
        "tags": [
          "Portal - mix Domain"
        ],
        "requestBody": {
          "content": {
            "application/json-patch+json": {
              "schema": {
                "type": "object",
                "additionalProperties": {
                  "$ref": "#/components/schemas/Newtonsoft.Json.Linq.JToken"
                }
              }
            },
            "application/json": {
              "schema": {
                "type": "object",
                "additionalProperties": {
                  "$ref": "#/components/schemas/Newtonsoft.Json.Linq.JToken"
                }
              }
            },
            "text/json": {
              "schema": {
                "type": "object",
                "additionalProperties": {
                  "$ref": "#/components/schemas/Newtonsoft.Json.Linq.JToken"
                }
              }
            },
            "application/*+json": {
              "schema": {
                "type": "object",
                "additionalProperties": {
                  "$ref": "#/components/schemas/Newtonsoft.Json.Linq.JToken"
                }
              }
            }
          }
        },
        "responses": {
          "200": {
            "description": "OK"
          }
        }
      },
      "get": {
        "tags": [
          "Portal - mix Domain"
        ],
        "parameters": [
          {
            "name": "LoadNestedData",
            "in": "query",
            "schema": {
              "type": "boolean"
            }
          },
          {
            "name": "MixDatabaseName",
            "in": "query",
            "schema": {
              "type": "string"
            }
          },
          {
            "name": "Keyword",
            "in": "query",
            "schema": {
              "type": "string"
            }
          },
          {
            "name": "Culture",
            "in": "query",
            "schema": {
              "type": "string"
            }
          },
          {
            "name": "FromDate",
            "in": "query",
            "schema": {
              "type": "string",
              "format": "date-time"
            }
          },
          {
            "name": "ToDate",
            "in": "query",
            "schema": {
              "type": "string",
              "format": "date-time"
            }
          },
          {
            "name": "PageIndex",
            "in": "query",
            "schema": {
              "type": "integer",
              "format": "int32"
            }
          },
          {
            "name": "PageSize",
            "in": "query",
            "schema": {
              "type": "integer",
              "format": "int32"
            }
          },
          {
            "name": "PagingState",
            "in": "query",
            "schema": {
              "type": "string"
            }
          },
          {
            "name": "SortBy",
            "in": "query",
            "schema": {
              "type": "string"
            }
          },
          {
            "name": "OrderBy",
            "in": "query",
            "schema": {
              "type": "string"
            }
          },
          {
            "name": "Conjunction",
            "in": "query",
            "schema": {
              "$ref": "#/components/schemas/Mix.Constant.Enums.MixConjunction"
            }
          },
          {
            "name": "Direction",
            "in": "query",
            "schema": {
              "$ref": "#/components/schemas/Mix.Heart.Enums.SortDirection"
            }
          },
          {
            "name": "Status",
            "in": "query",
            "schema": {
              "$ref": "#/components/schemas/Mix.Heart.Enums.MixContentStatus"
            }
          },
          {
            "name": "SearchMethod",
            "in": "query",
            "schema": {
              "$ref": "#/components/schemas/Mix.Constant.Enums.MixCompareOperator"
            }
          },
          {
            "name": "Columns",
            "in": "query",
            "schema": {
              "type": "string"
            }
          },
          {
            "name": "SearchColumns",
            "in": "query",
            "schema": {
              "type": "string"
            }
          },
          {
            "name": "After",
            "in": "query",
            "schema": {}
          },
          {
            "name": "Before",
            "in": "query",
            "schema": {}
          },
          {
            "name": "Queries",
            "in": "query",
            "schema": {
              "type": "array",
              "items": {
                "$ref": "#/components/schemas/Mix.Shared.Dtos.MixQueryField"
              }
            }
          },
          {
            "name": "SortByFields",
            "in": "query",
            "schema": {
              "type": "array",
              "items": {
                "$ref": "#/components/schemas/Mix.Heart.Model.MixSortByColumn"
              }
            }
          }
        ],
        "responses": {
          "200": {
            "description": "OK",
            "content": {
              "text/plain": {
                "schema": {
                  "$ref": "#/components/schemas/Mix.Heart.Models.PagingResponseModel`1[[Mix.Lib.ViewModels.MixDomainViewModel, mix.library, Version=1.0.0.0, Culture=neutral, PublicKeyToken=null]]"
                }
              },
              "application/json": {
                "schema": {
                  "$ref": "#/components/schemas/Mix.Heart.Models.PagingResponseModel`1[[Mix.Lib.ViewModels.MixDomainViewModel, mix.library, Version=1.0.0.0, Culture=neutral, PublicKeyToken=null]]"
                }
              },
              "text/json": {
                "schema": {
                  "$ref": "#/components/schemas/Mix.Heart.Models.PagingResponseModel`1[[Mix.Lib.ViewModels.MixDomainViewModel, mix.library, Version=1.0.0.0, Culture=neutral, PublicKeyToken=null]]"
                }
              }
            }
          }
        }
      }
    },
    "/api/v2/rest/mix-portal/mix-domain/{id}": {
      "put": {
        "tags": [
          "Portal - mix Domain"
        ],
        "parameters": [
          {
            "name": "id",
            "in": "path",
            "required": true,
            "schema": {
              "type": "integer",
              "format": "int32"
            }
          }
        ],
        "requestBody": {
          "content": {
            "application/json-patch+json": {
              "schema": {
                "$ref": "#/components/schemas/Mix.Lib.ViewModels.MixDomainViewModel"
              }
            },
            "application/json": {
              "schema": {
                "$ref": "#/components/schemas/Mix.Lib.ViewModels.MixDomainViewModel"
              }
            },
            "text/json": {
              "schema": {
                "$ref": "#/components/schemas/Mix.Lib.ViewModels.MixDomainViewModel"
              }
            },
            "application/*+json": {
              "schema": {
                "$ref": "#/components/schemas/Mix.Lib.ViewModels.MixDomainViewModel"
              }
            }
          }
        },
        "responses": {
          "200": {
            "description": "OK"
          }
        }
      },
      "delete": {
        "tags": [
          "Portal - mix Domain"
        ],
        "parameters": [
          {
            "name": "id",
            "in": "path",
            "required": true,
            "schema": {
              "type": "integer",
              "format": "int32"
            }
          }
        ],
        "responses": {
          "200": {
            "description": "OK"
          }
        }
      },
      "get": {
        "tags": [
          "Portal - mix Domain"
        ],
        "parameters": [
          {
            "name": "id",
            "in": "path",
            "required": true,
            "schema": {
              "type": "integer",
              "format": "int32"
            }
          }
        ],
        "responses": {
          "200": {
            "description": "OK",
            "content": {
              "text/plain": {
                "schema": {
                  "$ref": "#/components/schemas/Mix.Lib.ViewModels.MixDomainViewModel"
                }
              },
              "application/json": {
                "schema": {
                  "$ref": "#/components/schemas/Mix.Lib.ViewModels.MixDomainViewModel"
                }
              },
              "text/json": {
                "schema": {
                  "$ref": "#/components/schemas/Mix.Lib.ViewModels.MixDomainViewModel"
                }
              }
            }
          }
        }
      }
    },
    "/api/v2/rest/mix-portal/mix-domain/remove-cache/{id}": {
      "delete": {
        "tags": [
          "Portal - mix Domain"
        ],
        "parameters": [
          {
            "name": "id",
            "in": "path",
            "required": true,
            "schema": {
              "type": "integer",
              "format": "int32"
            }
          }
        ],
        "responses": {
          "200": {
            "description": "OK"
          }
        }
      }
    },
    "/api/v2/rest/mix-portal/mix-domain/patch-many": {
      "patch": {
        "tags": [
          "Portal - mix Domain"
        ],
        "requestBody": {
          "content": {
            "application/json-patch+json": {
              "schema": {
                "type": "array",
                "items": {
                  "type": "object",
                  "additionalProperties": {
                    "$ref": "#/components/schemas/Newtonsoft.Json.Linq.JToken"
                  }
                }
              }
            },
            "application/json": {
              "schema": {
                "type": "array",
                "items": {
                  "type": "object",
                  "additionalProperties": {
                    "$ref": "#/components/schemas/Newtonsoft.Json.Linq.JToken"
                  }
                }
              }
            },
            "text/json": {
              "schema": {
                "type": "array",
                "items": {
                  "type": "object",
                  "additionalProperties": {
                    "$ref": "#/components/schemas/Newtonsoft.Json.Linq.JToken"
                  }
                }
              }
            },
            "application/*+json": {
              "schema": {
                "type": "array",
                "items": {
                  "type": "object",
                  "additionalProperties": {
                    "$ref": "#/components/schemas/Newtonsoft.Json.Linq.JToken"
                  }
                }
              }
            }
          }
        },
        "responses": {
          "200": {
            "description": "OK"
          }
        }
      }
    },
    "/api/v2/rest/mix-portal/mix-domain/save-many": {
      "post": {
        "tags": [
          "Portal - mix Domain"
        ],
        "requestBody": {
          "content": {
            "application/json-patch+json": {
              "schema": {
                "type": "array",
                "items": {
                  "$ref": "#/components/schemas/Mix.Lib.ViewModels.MixDomainViewModel"
                }
              }
            },
            "application/json": {
              "schema": {
                "type": "array",
                "items": {
                  "$ref": "#/components/schemas/Mix.Lib.ViewModels.MixDomainViewModel"
                }
              }
            },
            "text/json": {
              "schema": {
                "type": "array",
                "items": {
                  "$ref": "#/components/schemas/Mix.Lib.ViewModels.MixDomainViewModel"
                }
              }
            },
            "application/*+json": {
              "schema": {
                "type": "array",
                "items": {
                  "$ref": "#/components/schemas/Mix.Lib.ViewModels.MixDomainViewModel"
                }
              }
            }
          }
        },
        "responses": {
          "200": {
            "description": "OK"
          }
        }
      }
    },
    "/api/v2/rest/mix-portal/mix-domain/filter": {
      "post": {
        "tags": [
          "Portal - mix Domain"
        ],
        "requestBody": {
          "content": {
            "application/json-patch+json": {
              "schema": {
                "$ref": "#/components/schemas/Mix.Shared.Dtos.SearchRequestDto"
              }
            },
            "application/json": {
              "schema": {
                "$ref": "#/components/schemas/Mix.Shared.Dtos.SearchRequestDto"
              }
            },
            "text/json": {
              "schema": {
                "$ref": "#/components/schemas/Mix.Shared.Dtos.SearchRequestDto"
              }
            },
            "application/*+json": {
              "schema": {
                "$ref": "#/components/schemas/Mix.Shared.Dtos.SearchRequestDto"
              }
            }
          }
        },
        "responses": {
          "200": {
            "description": "OK",
            "content": {
              "text/plain": {
                "schema": {
                  "$ref": "#/components/schemas/Mix.Heart.Models.PagingResponseModel`1[[Mix.Lib.ViewModels.MixDomainViewModel, mix.library, Version=1.0.0.0, Culture=neutral, PublicKeyToken=null]]"
                }
              },
              "application/json": {
                "schema": {
                  "$ref": "#/components/schemas/Mix.Heart.Models.PagingResponseModel`1[[Mix.Lib.ViewModels.MixDomainViewModel, mix.library, Version=1.0.0.0, Culture=neutral, PublicKeyToken=null]]"
                }
              },
              "text/json": {
                "schema": {
                  "$ref": "#/components/schemas/Mix.Heart.Models.PagingResponseModel`1[[Mix.Lib.ViewModels.MixDomainViewModel, mix.library, Version=1.0.0.0, Culture=neutral, PublicKeyToken=null]]"
                }
              }
            }
          }
        }
      }
    }
  }
}